DeviceControllerTelegramBot/__init__.py
DeviceControllerTelegramBot/__main__.py
DeviceControllerTelegramBot/bot.py
DeviceControllerTelegramBot/device_controller.py
DeviceControllerTelegramBot-1.0.0.dist-info/LICENSE.md
DeviceControllerTelegramBot-1.0.0.dist-info/METADATA
DeviceControllerTelegramBot-1.0.0.dist-info/WHEEL
DeviceControllerTelegramBot-1.0.0.dist-info/top_level.txt
DeviceControllerTelegramBot-1.0.0.dist-info/RECORD
