Metadata-Version: 2.1
Name: DeviceControllerTelegramBot
Version: 1.0.0
Summary: A Telegram Bot to control Board Pins for Device Controller Arduino Library
Home-page: UNKNOWN
Author: Dhrumil Mistry
License: MIT License
Platform: UNKNOWN
Requires-Dist: setuptools
Requires-Dist: pyserial
Requires-Dist: pyTelegramBotAPI
